{
	"id": 227760691,
	"sku": "GE779ST3MQXO4NAFAMZ",
	"title": "10 Piece Professional Styling Hair Comb Set",
	"name": "10 Piece Professional Styling Hair Comb Set",
	"price": "1999.00",
	"currency": "₦",
	"rating": {
		"average": 4,
		"totalRatings": 1459
	},
	"url": "https://www.jumia.com.ng/generic-10-piece-professional-styling-hair-comb-set-227760691.html",
	"categories": [
		"Health & Beauty",
		"Beauty & Personal Care",
		"Hair Care",
		"Styling Tools & Appliances",
		"Hair Combs"
	],
	"images": [
		"https://ng.jumia.is/unsafe/fit-in/300x300/filters:fill(white)/product/19/6067722/1.jpg?5555",
		"https://ng.jumia.is/unsafe/fit-in/680x680/filters:fill(white)/product/19/6067722/1.jpg?5555",
		"https://ng.jumia.is/unsafe/fit-in/680x680/filters:fill(white)/product/19/6067722/2.jpg?5555",
		"https://ng.jumia.is/unsafe/fit-in/680x680/filters:fill(white)/product/19/6067722/3.jpg?5555"
	]
}