{
	"id": "mOPcCVO6NGUc92c",
	"json": "{\"id\":\"mOPcCVO6NGUc92c\",\"url\":\"https://www.jumia.com.ng/zaron-brownskin-foundation-291120831.html\",\"uniqueKey\":\"https://www.jumia.com.ng/zaron-brownskin-foundation-291120831.html\",\"method\":\"GET\",\"noRetry\":false,\"retryCount\":0,\"errorMessages\":[],\"headers\":{},\"userData\":{\"label\":\"PRODUCT\"}}",
	"method": "GET",
	"orderNo": 1734961758844,
	"retryCount": 0,
	"uniqueKey": "https://www.jumia.com.ng/zaron-brownskin-foundation-291120831.html",
	"url": "https://www.jumia.com.ng/zaron-brownskin-foundation-291120831.html"
}